test/__init__.py
test/test_tvarit.py
test/api/__init__.py
test/api/test_team.py
tvarit_api/__init__.py
tvarit_api/api.py
tvarit_api/tvarit.py
tvarit_api/version.py
tvarit_api/resources/__init__.py
tvarit_api/resources/admin.py
tvarit_api/resources/alerting.py
tvarit_api/resources/annotations.py
tvarit_api/resources/base.py
tvarit_api/resources/dashboard.py
tvarit_api/resources/datasource.py
tvarit_api/resources/folder.py
tvarit_api/resources/handler.py
tvarit_api/resources/job.py
tvarit_api/resources/machine.py
tvarit_api/resources/model.py
tvarit_api/resources/organization.py
tvarit_api/resources/output.py
tvarit_api/resources/parameter.py
tvarit_api/resources/pipeline.py
tvarit_api/resources/search.py
tvarit_api/resources/snapshot.py
tvarit_api/resources/task.py
tvarit_api/resources/team.py
tvarit_api/resources/user.py
tvarit_api-1.3.1.dist-info/LICENSE
tvarit_api-1.3.1.dist-info/METADATA
tvarit_api-1.3.1.dist-info/WHEEL
tvarit_api-1.3.1.dist-info/top_level.txt
tvarit_api-1.3.1.dist-info/RECORD
